hello_world/__init__.py
77_myfirst_hwwo_lib_77_2025-0.1.1.dist-info/METADATA
77_myfirst_hwwo_lib_77_2025-0.1.1.dist-info/WHEEL
77_myfirst_hwwo_lib_77_2025-0.1.1.dist-info/top_level.txt
77_myfirst_hwwo_lib_77_2025-0.1.1.dist-info/RECORD
